clingo_lpx-1.3.0.post1.dist-info/LICENSE
clingo_lpx-1.3.0.post1.dist-info/WHEEL
clingo_lpx-1.3.0.post1.dist-info/METADATA
clingo_lpx-1.3.0.post1.dist-info/top_level.txt
clingo_lpx-1.3.0.post1.dist-info/RECORD
clingolpx/_clingolpx.cpython-312-i386-linux-gnu.so
clingolpx/__init__.py
clingolpx/clingo-lpx.h
clingolpx/__main__.py
clingolpx/py.typed
