Metadata-Version: 2.1
Name: clingo-lpx
Version: 1.3.0.post1
Summary: CFFI-based bindings to the clingo-lpx solver.
Home-page: https://github.com/potassco/clingo-lpx
Author: Roland Kaminski
Author-email: kaminski@cs.uni-potsdam.de
License: MIT
Requires-Python: >=3.6
License-File: LICENSE
Requires-Dist: cffi
Requires-Dist: clingo
